opensky_sv/__init__.py
opensky_sv/asv.py
opensky_sv/cities.py
opensky_sv-0.0.1.dist-info/METADATA
opensky_sv-0.0.1.dist-info/RECORD
opensky_sv-0.0.1.dist-info/WHEEL
opensky_sv-0.0.1.dist-info/top_level.txt
