Metadata-Version: 2.1
Name: opensky-sv
Version: 0.0.1
Summary: A library for Opensky Network
Home-page: https://github.com/sm-svyat/opensky_asv
Author: UNKNOWN
Author-email: UNKNOWN
License: UNKNOWN
Platform: UNKNOWN
